{"cityid": 227355, "citynamestate": "Peachtree City, Georgia", "statecode": "GA", "timezone": "UTC-5 Eastern", "latitude": 33.3967829, "logitude": -84.59576290000003, "fpis": "13-59724", "gnis": null, "wikiimgurl": "https://upload.wikimedia.org/wikipedia/commons/thumb/2/2e/Lake_Peachtree_Bridge.jpg/500px-Lake_Peachtree_Bridge.jpg", "website": "www.peachtree-city.org", "population": 35262.0, "densitymisq": 1440.74, "densitykmsq": 556.28, "averageage": 41.9, "householdincome": 93974.0, "individualincome": 44048.0, "averagehouse": 329510.0, "rent": 1452.0, "costoflivingindex": 97.4, "acastatus": "Not Adopted", "averagetemp": 64.64999999999999, "averageperc": 4.7525, "avgnewcovidcases": 571.0792452830188, "zipcodes": [{"code": "30269"}], "counties": [{"name": "Fayette"}], "populationhist": [{"year": 2010, "pop": 34364.0}, {"year": 2011, "pop": 34536.0}, {"year": 2012, "pop": 34576.0}, {"year": 2013, "pop": 34738.0}, {"year": 2014, "pop": 34869.0}, {"year": 2015, "pop": 35000.0}, {"year": 2016, "pop": 34994.0}, {"year": 2017, "pop": 35280.0}, {"year": 2018, "pop": 35697.0}, {"year": 2019, "pop": 36223.0}], "historicalincome": [{"year": 2019, "individualincome": 37881, "householdincome": 61980}, {"year": 2018, "individualincome": 36155, "householdincome": 58756}, {"year": 2017, "individualincome": 34224, "householdincome": 56183}, {"year": 2016, "individualincome": 33209, "householdincome": 53559}, {"year": 2015, "individualincome": 31834, "householdincome": 51244}, {"year": 2014, "individualincome": 31104, "householdincome": 49321}, {"year": 2013, "individualincome": 30276, "householdincome": 47829}, {"year": 2012, "individualincome": 29479, "householdincome": 47209}, {"year": 2011, "individualincome": 28217, "householdincome": 46007}, {"year": 2010, "individualincome": 28496, "householdincome": 46430}], "historicalaveragehouse": [{"year": 2010, "month": 1, "housingcost": 251490}, {"year": 2010, "month": 2, "housingcost": 252340}, {"year": 2010, "month": 3, "housingcost": 252305}, {"year": 2010, "month": 4, "housingcost": 250995}, {"year": 2010, "month": 5, "housingcost": 251559}, {"year": 2010, "month": 6, "housingcost": 250909}, {"year": 2010, "month": 7, "housingcost": 250377}, {"year": 2010, "month": 8, "housingcost": 248168}, {"year": 2010, "month": 9, "housingcost": 246971}, {"year": 2010, "month": 10, "housingcost": 245962}, {"year": 2010, "month": 11, "housingcost": 245109}, {"year": 2010, "month": 12, "housingcost": 242507}, {"year": 2011, "month": 1, "housingcost": 238564}, {"year": 2011, "month": 2, "housingcost": 233001}, {"year": 2011, "month": 3, "housingcost": 228981}, {"year": 2011, "month": 4, "housingcost": 227201}, {"year": 2011, "month": 5, "housingcost": 225476}, {"year": 2011, "month": 6, "housingcost": 223445}, {"year": 2011, "month": 7, "housingcost": 221141}, {"year": 2011, "month": 8, "housingcost": 220164}, {"year": 2011, "month": 9, "housingcost": 219819}, {"year": 2011, "month": 10, "housingcost": 220708}, {"year": 2011, "month": 11, "housingcost": 219983}, {"year": 2011, "month": 12, "housingcost": 219367}, {"year": 2012, "month": 1, "housingcost": 217799}, {"year": 2012, "month": 2, "housingcost": 220666}, {"year": 2012, "month": 3, "housingcost": 223142}, {"year": 2012, "month": 4, "housingcost": 224728}, {"year": 2012, "month": 5, "housingcost": 225017}, {"year": 2012, "month": 6, "housingcost": 227164}, {"year": 2012, "month": 7, "housingcost": 229853}, {"year": 2012, "month": 8, "housingcost": 231286}, {"year": 2012, "month": 9, "housingcost": 230505}, {"year": 2012, "month": 10, "housingcost": 229210}, {"year": 2012, "month": 11, "housingcost": 230662}, {"year": 2012, "month": 12, "housingcost": 235165}, {"year": 2013, "month": 1, "housingcost": 242090}, {"year": 2013, "month": 2, "housingcost": 245193}, {"year": 2013, "month": 3, "housingcost": 246576}, {"year": 2013, "month": 4, "housingcost": 246258}, {"year": 2013, "month": 5, "housingcost": 247443}, {"year": 2013, "month": 6, "housingcost": 247644}, {"year": 2013, "month": 7, "housingcost": 248120}, {"year": 2013, "month": 8, "housingcost": 249582}, {"year": 2013, "month": 9, "housingcost": 253103}, {"year": 2013, "month": 10, "housingcost": 256744}, {"year": 2013, "month": 11, "housingcost": 259419}, {"year": 2013, "month": 12, "housingcost": 259298}, {"year": 2014, "month": 1, "housingcost": 257444}, {"year": 2014, "month": 2, "housingcost": 256570}, {"year": 2014, "month": 3, "housingcost": 258373}, {"year": 2014, "month": 4, "housingcost": 262752}, {"year": 2014, "month": 5, "housingcost": 266444}, {"year": 2014, "month": 6, "housingcost": 269855}, {"year": 2014, "month": 7, "housingcost": 272432}, {"year": 2014, "month": 8, "housingcost": 274217}, {"year": 2014, "month": 9, "housingcost": 274808}, {"year": 2014, "month": 10, "housingcost": 274910}, {"year": 2014, "month": 11, "housingcost": 274960}, {"year": 2014, "month": 12, "housingcost": 276170}, {"year": 2015, "month": 1, "housingcost": 278239}, {"year": 2015, "month": 2, "housingcost": 280259}, {"year": 2015, "month": 3, "housingcost": 280961}, {"year": 2015, "month": 4, "housingcost": 280792}, {"year": 2015, "month": 5, "housingcost": 280902}, {"year": 2015, "month": 6, "housingcost": 281341}, {"year": 2015, "month": 7, "housingcost": 281819}, {"year": 2015, "month": 8, "housingcost": 283355}, {"year": 2015, "month": 9, "housingcost": 285205}, {"year": 2015, "month": 10, "housingcost": 287287}, {"year": 2015, "month": 11, "housingcost": 288405}, {"year": 2015, "month": 12, "housingcost": 289113}, {"year": 2016, "month": 1, "housingcost": 289726}, {"year": 2016, "month": 2, "housingcost": 290645}, {"year": 2016, "month": 3, "housingcost": 291946}, {"year": 2016, "month": 4, "housingcost": 292927}, {"year": 2016, "month": 5, "housingcost": 294238}, {"year": 2016, "month": 6, "housingcost": 295688}, {"year": 2016, "month": 7, "housingcost": 297764}, {"year": 2016, "month": 8, "housingcost": 298978}, {"year": 2016, "month": 9, "housingcost": 300387}, {"year": 2016, "month": 10, "housingcost": 301476}, {"year": 2016, "month": 11, "housingcost": 304238}, {"year": 2016, "month": 12, "housingcost": 306714}, {"year": 2017, "month": 1, "housingcost": 309570}, {"year": 2017, "month": 2, "housingcost": 311684}, {"year": 2017, "month": 3, "housingcost": 313474}, {"year": 2017, "month": 4, "housingcost": 316220}, {"year": 2017, "month": 5, "housingcost": 318472}, {"year": 2017, "month": 6, "housingcost": 320719}, {"year": 2017, "month": 7, "housingcost": 321471}, {"year": 2017, "month": 8, "housingcost": 323009}, {"year": 2017, "month": 9, "housingcost": 324566}, {"year": 2017, "month": 10, "housingcost": 326715}, {"year": 2017, "month": 11, "housingcost": 327565}, {"year": 2017, "month": 12, "housingcost": 328310}, {"year": 2018, "month": 1, "housingcost": 328740}, {"year": 2018, "month": 2, "housingcost": 329530}, {"year": 2018, "month": 3, "housingcost": 331506}, {"year": 2018, "month": 4, "housingcost": 332423}, {"year": 2018, "month": 5, "housingcost": 333571}, {"year": 2018, "month": 6, "housingcost": 333852}, {"year": 2018, "month": 7, "housingcost": 335654}, {"year": 2018, "month": 8, "housingcost": 337262}, {"year": 2018, "month": 9, "housingcost": 338223}, {"year": 2018, "month": 10, "housingcost": 339006}, {"year": 2018, "month": 11, "housingcost": 340055}, {"year": 2018, "month": 12, "housingcost": 341275}, {"year": 2019, "month": 1, "housingcost": 341155}, {"year": 2019, "month": 2, "housingcost": 341504}, {"year": 2019, "month": 3, "housingcost": 341798}, {"year": 2019, "month": 4, "housingcost": 343446}, {"year": 2019, "month": 5, "housingcost": 343450}, {"year": 2019, "month": 6, "housingcost": 343956}, {"year": 2019, "month": 7, "housingcost": 343498}, {"year": 2019, "month": 8, "housingcost": 344116}, {"year": 2019, "month": 9, "housingcost": 344990}, {"year": 2019, "month": 10, "housingcost": 345906}, {"year": 2019, "month": 11, "housingcost": 346665}, {"year": 2019, "month": 12, "housingcost": 347461}, {"year": 2020, "month": 1, "housingcost": 349408}, {"year": 2020, "month": 2, "housingcost": 351001}, {"year": 2020, "month": 3, "housingcost": 352139}, {"year": 2020, "month": 4, "housingcost": 352610}, {"year": 2020, "month": 5, "housingcost": 354402}, {"year": 2020, "month": 6, "housingcost": 356322}, {"year": 2020, "month": 7, "housingcost": 358641}, {"year": 2020, "month": 8, "housingcost": 360207}], "covid": [{"year": 2020, "month": 1, "day": 22, "cases": 0}, {"year": 2020, "month": 1, "day": 23, "cases": 0}, {"year": 2020, "month": 1, "day": 24, "cases": 0}, {"year": 2020, "month": 1, "day": 25, "cases": 0}, {"year": 2020, "month": 1, "day": 26, "cases": 0}, {"year": 2020, "month": 1, "day": 27, "cases": 0}, {"year": 2020, "month": 1, "day": 28, "cases": 0}, {"year": 2020, "month": 1, "day": 29, "cases": 0}, {"year": 2020, "month": 1, "day": 30, "cases": 0}, {"year": 2020, "month": 1, "day": 31, "cases": 0}, {"year": 2020, "month": 2, "day": 1, "cases": 0}, {"year": 2020, "month": 2, "day": 2, "cases": 0}, {"year": 2020, "month": 2, "day": 3, "cases": 0}, {"year": 2020, "month": 2, "day": 4, "cases": 0}, {"year": 2020, "month": 2, "day": 5, "cases": 0}, {"year": 2020, "month": 2, "day": 6, "cases": 0}, {"year": 2020, "month": 2, "day": 7, "cases": 0}, {"year": 2020, "month": 2, "day": 8, "cases": 0}, {"year": 2020, "month": 2, "day": 9, "cases": 0}, {"year": 2020, "month": 2, "day": 10, "cases": 0}, {"year": 2020, "month": 2, "day": 11, "cases": 0}, {"year": 2020, "month": 2, "day": 12, "cases": 0}, {"year": 2020, "month": 2, "day": 13, "cases": 0}, {"year": 2020, "month": 2, "day": 14, "cases": 0}, {"year": 2020, "month": 2, "day": 15, "cases": 0}, {"year": 2020, "month": 2, "day": 16, "cases": 0}, {"year": 2020, "month": 2, "day": 17, "cases": 0}, {"year": 2020, "month": 2, "day": 18, "cases": 0}, {"year": 2020, "month": 2, "day": 19, "cases": 0}, {"year": 2020, "month": 2, "day": 20, "cases": 0}, {"year": 2020, "month": 2, "day": 21, "cases": 0}, {"year": 2020, "month": 2, "day": 22, "cases": 0}, {"year": 2020, "month": 2, "day": 23, "cases": 0}, {"year": 2020, "month": 2, "day": 24, "cases": 0}, {"year": 2020, "month": 2, "day": 25, "cases": 0}, {"year": 2020, "month": 2, "day": 26, "cases": 0}, {"year": 2020, "month": 2, "day": 27, "cases": 0}, {"year": 2020, "month": 2, "day": 28, "cases": 0}, {"year": 2020, "month": 2, "day": 29, "cases": 0}, {"year": 2020, "month": 3, "day": 1, "cases": 0}, {"year": 2020, "month": 3, "day": 2, "cases": 0}, {"year": 2020, "month": 3, "day": 3, "cases": 0}, {"year": 2020, "month": 3, "day": 4, "cases": 0}, {"year": 2020, "month": 3, "day": 5, "cases": 0}, {"year": 2020, "month": 3, "day": 6, "cases": 0}, {"year": 2020, "month": 3, "day": 7, "cases": 0}, {"year": 2020, "month": 3, "day": 8, "cases": 0}, {"year": 2020, "month": 3, "day": 9, "cases": 0}, {"year": 2020, "month": 3, "day": 10, "cases": 1}, {"year": 2020, "month": 3, "day": 11, "cases": 1}, {"year": 2020, "month": 3, "day": 12, "cases": 1}, {"year": 2020, "month": 3, "day": 13, "cases": 3}, {"year": 2020, "month": 3, "day": 14, "cases": 4}, {"year": 2020, "month": 3, "day": 15, "cases": 5}, {"year": 2020, "month": 3, "day": 16, "cases": 5}, {"year": 2020, "month": 3, "day": 17, "cases": 5}, {"year": 2020, "month": 3, "day": 18, "cases": 8}, {"year": 2020, "month": 3, "day": 19, "cases": 10}, {"year": 2020, "month": 3, "day": 20, "cases": 9}, {"year": 2020, "month": 3, "day": 21, "cases": 9}, {"year": 2020, "month": 3, "day": 22, "cases": 9}, {"year": 2020, "month": 3, "day": 23, "cases": 10}, {"year": 2020, "month": 3, "day": 24, "cases": 12}, {"year": 2020, "month": 3, "day": 25, "cases": 12}, {"year": 2020, "month": 3, "day": 26, "cases": 14}, {"year": 2020, "month": 3, "day": 27, "cases": 19}, {"year": 2020, "month": 3, "day": 28, "cases": 25}, {"year": 2020, "month": 3, "day": 29, "cases": 26}, {"year": 2020, "month": 3, "day": 30, "cases": 32}, {"year": 2020, "month": 3, "day": 31, "cases": 45}, {"year": 2020, "month": 4, "day": 1, "cases": 48}, {"year": 2020, "month": 4, "day": 2, "cases": 52}, {"year": 2020, "month": 4, "day": 3, "cases": 58}, {"year": 2020, "month": 4, "day": 4, "cases": 62}, {"year": 2020, "month": 4, "day": 5, "cases": 67}, {"year": 2020, "month": 4, "day": 6, "cases": 74}, {"year": 2020, "month": 4, "day": 7, "cases": 79}, {"year": 2020, "month": 4, "day": 8, "cases": 85}, {"year": 2020, "month": 4, "day": 9, "cases": 89}, {"year": 2020, "month": 4, "day": 10, "cases": 92}, {"year": 2020, "month": 4, "day": 11, "cases": 94}, {"year": 2020, "month": 4, "day": 12, "cases": 99}, {"year": 2020, "month": 4, "day": 13, "cases": 105}, {"year": 2020, "month": 4, "day": 14, "cases": 115}, {"year": 2020, "month": 4, "day": 15, "cases": 120}, {"year": 2020, "month": 4, "day": 16, "cases": 124}, {"year": 2020, "month": 4, "day": 17, "cases": 133}, {"year": 2020, "month": 4, "day": 18, "cases": 135}, {"year": 2020, "month": 4, "day": 19, "cases": 139}, {"year": 2020, "month": 4, "day": 20, "cases": 143}, {"year": 2020, "month": 4, "day": 21, "cases": 144}, {"year": 2020, "month": 4, "day": 22, "cases": 146}, {"year": 2020, "month": 4, "day": 23, "cases": 156}, {"year": 2020, "month": 4, "day": 24, "cases": 158}, {"year": 2020, "month": 4, "day": 25, "cases": 161}, {"year": 2020, "month": 4, "day": 26, "cases": 161}, {"year": 2020, "month": 4, "day": 27, "cases": 169}, {"year": 2020, "month": 4, "day": 28, "cases": 171}, {"year": 2020, "month": 4, "day": 29, "cases": 174}, {"year": 2020, "month": 4, "day": 30, "cases": 176}, {"year": 2020, "month": 5, "day": 1, "cases": 178}, {"year": 2020, "month": 5, "day": 2, "cases": 181}, {"year": 2020, "month": 5, "day": 3, "cases": 183}, {"year": 2020, "month": 5, "day": 4, "cases": 187}, {"year": 2020, "month": 5, "day": 5, "cases": 189}, {"year": 2020, "month": 5, "day": 6, "cases": 188}, {"year": 2020, "month": 5, "day": 7, "cases": 191}, {"year": 2020, "month": 5, "day": 8, "cases": 190}, {"year": 2020, "month": 5, "day": 9, "cases": 195}, {"year": 2020, "month": 5, "day": 10, "cases": 199}, {"year": 2020, "month": 5, "day": 11, "cases": 201}, {"year": 2020, "month": 5, "day": 12, "cases": 202}, {"year": 2020, "month": 5, "day": 13, "cases": 202}, {"year": 2020, "month": 5, "day": 14, "cases": 204}, {"year": 2020, "month": 5, "day": 15, "cases": 205}, {"year": 2020, "month": 5, "day": 16, "cases": 206}, {"year": 2020, "month": 5, "day": 17, "cases": 207}, {"year": 2020, "month": 5, "day": 18, "cases": 210}, {"year": 2020, "month": 5, "day": 19, "cases": 212}, {"year": 2020, "month": 5, "day": 20, "cases": 215}, {"year": 2020, "month": 5, "day": 21, "cases": 212}, {"year": 2020, "month": 5, "day": 22, "cases": 215}, {"year": 2020, "month": 5, "day": 23, "cases": 219}, {"year": 2020, "month": 5, "day": 24, "cases": 220}, {"year": 2020, "month": 5, "day": 25, "cases": 221}, {"year": 2020, "month": 5, "day": 26, "cases": 232}, {"year": 2020, "month": 5, "day": 27, "cases": 235}, {"year": 2020, "month": 5, "day": 28, "cases": 231}, {"year": 2020, "month": 5, "day": 29, "cases": 234}, {"year": 2020, "month": 5, "day": 30, "cases": 235}, {"year": 2020, "month": 5, "day": 31, "cases": 235}, {"year": 2020, "month": 6, "day": 1, "cases": 235}, {"year": 2020, "month": 6, "day": 2, "cases": 237}, {"year": 2020, "month": 6, "day": 3, "cases": 239}, {"year": 2020, "month": 6, "day": 4, "cases": 241}, {"year": 2020, "month": 6, "day": 5, "cases": 244}, {"year": 2020, "month": 6, "day": 6, "cases": 245}, {"year": 2020, "month": 6, "day": 7, "cases": 245}, {"year": 2020, "month": 6, "day": 8, "cases": 247}, {"year": 2020, "month": 6, "day": 9, "cases": 254}, {"year": 2020, "month": 6, "day": 10, "cases": 254}, {"year": 2020, "month": 6, "day": 11, "cases": 258}, {"year": 2020, "month": 6, "day": 12, "cases": 259}, {"year": 2020, "month": 6, "day": 13, "cases": 260}, {"year": 2020, "month": 6, "day": 14, "cases": 261}, {"year": 2020, "month": 6, "day": 15, "cases": 261}, {"year": 2020, "month": 6, "day": 16, "cases": 270}, {"year": 2020, "month": 6, "day": 17, "cases": 271}, {"year": 2020, "month": 6, "day": 18, "cases": 271}, {"year": 2020, "month": 6, "day": 19, "cases": 278}, {"year": 2020, "month": 6, "day": 20, "cases": 279}, {"year": 2020, "month": 6, "day": 21, "cases": 280}, {"year": 2020, "month": 6, "day": 22, "cases": 292}, {"year": 2020, "month": 6, "day": 23, "cases": 299}, {"year": 2020, "month": 6, "day": 24, "cases": 305}, {"year": 2020, "month": 6, "day": 25, "cases": 314}, {"year": 2020, "month": 6, "day": 26, "cases": 322}, {"year": 2020, "month": 6, "day": 27, "cases": 324}, {"year": 2020, "month": 6, "day": 28, "cases": 326}, {"year": 2020, "month": 6, "day": 29, "cases": 326}, {"year": 2020, "month": 6, "day": 30, "cases": 341}, {"year": 2020, "month": 7, "day": 1, "cases": 346}, {"year": 2020, "month": 7, "day": 2, "cases": 363}, {"year": 2020, "month": 7, "day": 3, "cases": 384}, {"year": 2020, "month": 7, "day": 4, "cases": 408}, {"year": 2020, "month": 7, "day": 5, "cases": 414}, {"year": 2020, "month": 7, "day": 6, "cases": 422}, {"year": 2020, "month": 7, "day": 7, "cases": 458}, {"year": 2020, "month": 7, "day": 8, "cases": 472}, {"year": 2020, "month": 7, "day": 9, "cases": 476}, {"year": 2020, "month": 7, "day": 10, "cases": 498}, {"year": 2020, "month": 7, "day": 11, "cases": 509}, {"year": 2020, "month": 7, "day": 12, "cases": 514}, {"year": 2020, "month": 7, "day": 13, "cases": 532}, {"year": 2020, "month": 7, "day": 14, "cases": 549}, {"year": 2020, "month": 7, "day": 15, "cases": 565}, {"year": 2020, "month": 7, "day": 16, "cases": 584}, {"year": 2020, "month": 7, "day": 17, "cases": 612}, {"year": 2020, "month": 7, "day": 18, "cases": 629}, {"year": 2020, "month": 7, "day": 19, "cases": 654}, {"year": 2020, "month": 7, "day": 20, "cases": 669}, {"year": 2020, "month": 7, "day": 21, "cases": 693}, {"year": 2020, "month": 7, "day": 22, "cases": 702}, {"year": 2020, "month": 7, "day": 23, "cases": 742}, {"year": 2020, "month": 7, "day": 24, "cases": 764}, {"year": 2020, "month": 7, "day": 25, "cases": 788}, {"year": 2020, "month": 7, "day": 26, "cases": 805}, {"year": 2020, "month": 7, "day": 27, "cases": 825}, {"year": 2020, "month": 7, "day": 28, "cases": 855}, {"year": 2020, "month": 7, "day": 29, "cases": 873}, {"year": 2020, "month": 7, "day": 30, "cases": 898}, {"year": 2020, "month": 7, "day": 31, "cases": 918}, {"year": 2020, "month": 8, "day": 1, "cases": 949}, {"year": 2020, "month": 8, "day": 2, "cases": 970}, {"year": 2020, "month": 8, "day": 3, "cases": 980}, {"year": 2020, "month": 8, "day": 4, "cases": 994}, {"year": 2020, "month": 8, "day": 5, "cases": 1028}, {"year": 2020, "month": 8, "day": 6, "cases": 1047}, {"year": 2020, "month": 8, "day": 7, "cases": 1078}, {"year": 2020, "month": 8, "day": 8, "cases": 1100}, {"year": 2020, "month": 8, "day": 9, "cases": 1120}, {"year": 2020, "month": 8, "day": 10, "cases": 1131}, {"year": 2020, "month": 8, "day": 11, "cases": 1159}, {"year": 2020, "month": 8, "day": 12, "cases": 1187}, {"year": 2020, "month": 8, "day": 13, "cases": 1210}, {"year": 2020, "month": 8, "day": 14, "cases": 1243}, {"year": 2020, "month": 8, "day": 15, "cases": 1263}, {"year": 2020, "month": 8, "day": 16, "cases": 1277}, {"year": 2020, "month": 8, "day": 17, "cases": 1305}, {"year": 2020, "month": 8, "day": 18, "cases": 1341}, {"year": 2020, "month": 8, "day": 19, "cases": 1365}, {"year": 2020, "month": 8, "day": 20, "cases": 1388}, {"year": 2020, "month": 8, "day": 21, "cases": 1394}, {"year": 2020, "month": 8, "day": 22, "cases": 1404}, {"year": 2020, "month": 8, "day": 23, "cases": 1412}, {"year": 2020, "month": 8, "day": 24, "cases": 1419}, {"year": 2020, "month": 8, "day": 25, "cases": 1434}, {"year": 2020, "month": 8, "day": 26, "cases": 1453}, {"year": 2020, "month": 8, "day": 27, "cases": 1492}, {"year": 2020, "month": 8, "day": 28, "cases": 1539}, {"year": 2020, "month": 8, "day": 29, "cases": 1564}, {"year": 2020, "month": 8, "day": 30, "cases": 1568}, {"year": 2020, "month": 8, "day": 31, "cases": 1573}, {"year": 2020, "month": 9, "day": 1, "cases": 1585}, {"year": 2020, "month": 9, "day": 2, "cases": 1595}, {"year": 2020, "month": 9, "day": 3, "cases": 1606}, {"year": 2020, "month": 9, "day": 4, "cases": 1613}, {"year": 2020, "month": 9, "day": 5, "cases": 1624}, {"year": 2020, "month": 9, "day": 6, "cases": 1628}, {"year": 2020, "month": 9, "day": 7, "cases": 1628}, {"year": 2020, "month": 9, "day": 8, "cases": 1632}, {"year": 2020, "month": 9, "day": 9, "cases": 1644}, {"year": 2020, "month": 9, "day": 10, "cases": 1653}, {"year": 2020, "month": 9, "day": 11, "cases": 1657}, {"year": 2020, "month": 9, "day": 12, "cases": 1667}, {"year": 2020, "month": 9, "day": 13, "cases": 1675}, {"year": 2020, "month": 9, "day": 14, "cases": 1681}, {"year": 2020, "month": 9, "day": 15, "cases": 1693}, {"year": 2020, "month": 9, "day": 16, "cases": 1701}, {"year": 2020, "month": 9, "day": 17, "cases": 1715}, {"year": 2020, "month": 9, "day": 18, "cases": 1725}, {"year": 2020, "month": 9, "day": 19, "cases": 1734}, {"year": 2020, "month": 9, "day": 20, "cases": 1745}, {"year": 2020, "month": 9, "day": 21, "cases": 1752}, {"year": 2020, "month": 9, "day": 22, "cases": 1754}, {"year": 2020, "month": 9, "day": 23, "cases": 1763}, {"year": 2020, "month": 9, "day": 24, "cases": 1789}, {"year": 2020, "month": 9, "day": 25, "cases": 1808}, {"year": 2020, "month": 9, "day": 26, "cases": 1840}, {"year": 2020, "month": 9, "day": 27, "cases": 1850}, {"year": 2020, "month": 9, "day": 28, "cases": 1855}, {"year": 2020, "month": 9, "day": 29, "cases": 1860}, {"year": 2020, "month": 9, "day": 30, "cases": 1877}, {"year": 2020, "month": 10, "day": 1, "cases": 1896}, {"year": 2020, "month": 10, "day": 2, "cases": 1906}, {"year": 2020, "month": 10, "day": 3, "cases": 1914}, {"year": 2020, "month": 10, "day": 4, "cases": 1922}, {"year": 2020, "month": 10, "day": 5, "cases": 1925}, {"year": 2020, "month": 10, "day": 6, "cases": 1931}, {"year": 2020, "month": 10, "day": 7, "cases": 1937}, {"year": 2020, "month": 10, "day": 8, "cases": 1947}, {"year": 2020, "month": 10, "day": 9, "cases": 1954}, {"year": 2020, "month": 10, "day": 10, "cases": 1953}, {"year": 2020, "month": 10, "day": 11, "cases": 1962}, {"year": 2020, "month": 10, "day": 12, "cases": 1966}], "historicalweather": [{"month": "Sep", "precipitation": 1.69, "temperature": 79.5}, {"month": "Mar", "precipitation": 3.15, "temperature": 54.1}, {"month": "Nov", "precipitation": 3.86, "temperature": 50.5}, {"month": "Apr", "precipitation": 7.81, "temperature": 63.1}, {"month": "Dec", "precipitation": 7.74, "temperature": 50.2}, {"month": "Jan", "precipitation": 7.18, "temperature": 44.9}, {"month": "Jun", "precipitation": 9.7, "temperature": 76.5}, {"month": "Oct", "precipitation": 2.97, "temperature": 68.0}, {"month": "Jul", "precipitation": 4.98, "temperature": 80.7}, {"month": "May", "precipitation": 2.18, "temperature": 74.4}, {"month": "Feb", "precipitation": 3.77, "temperature": 52.8}, {"month": "Aug", "precipitation": 2.0, "temperature": 81.1}]}