{"cityid": 204469, "citynamestate": "Redwood City, California", "statecode": "CA", "timezone": "UTC-8 Pacific", "latitude": 37.4863239, "logitude": -122.2325233, "fpis": "06-6010", "gnis": null, "wikiimgurl": "https://upload.wikimedia.org/wikipedia/commons/thumb/b/b4/Redwoodcitypanorama.jpg/500px-Redwoodcitypanorama.jpg", "website": "www.redwoodcity.org", "population": 86685.0, "densitymisq": 4443.55, "densitykmsq": 1715.71, "averageage": 38.4, "householdincome": 116966.0, "individualincome": 58060.0, "averagehouse": 1196500.0, "rent": 2327.0, "costoflivingindex": 173.8, "acastatus": "Adopted", "averagetemp": 59.724999999999994, "averageperc": 1.8699999999999999, "avgnewcovidcases": 3411.966037735849, "zipcodes": [{"code": "94059"}, {"code": "94061\u00e2\u20ac\u201c94065"}], "counties": [{"name": "San"}, {"name": "Mateo"}], "populationhist": [{"year": 2010, "pop": 76815.0}, {"year": 2011, "pop": 77970.0}, {"year": 2012, "pop": 79188.0}, {"year": 2013, "pop": 81034.0}, {"year": 2014, "pop": 82741.0}, {"year": 2015, "pop": 85274.0}, {"year": 2016, "pop": 85293.0}, {"year": 2017, "pop": 86394.0}, {"year": 2018, "pop": 86105.0}, {"year": 2019, "pop": 85925.0}], "historicalincome": [{"year": 2019, "individualincome": 51676, "householdincome": 80440}, {"year": 2018, "individualincome": 48563, "householdincome": 75277}, {"year": 2017, "individualincome": 46599, "householdincome": 71805}, {"year": 2016, "individualincome": 44115, "householdincome": 67739}, {"year": 2015, "individualincome": 42068, "householdincome": 64500}, {"year": 2014, "individualincome": 40842, "householdincome": 61933}, {"year": 2013, "individualincome": 40319, "householdincome": 60190}, {"year": 2012, "individualincome": 39504, "householdincome": 58328}, {"year": 2011, "individualincome": 37584, "householdincome": 57287}, {"year": 2010, "individualincome": 38460, "householdincome": 57708}], "historicalaveragehouse": [{"year": 2010, "month": 1, "housingcost": 756225}, {"year": 2010, "month": 2, "housingcost": 757469}, {"year": 2010, "month": 3, "housingcost": 752813}, {"year": 2010, "month": 4, "housingcost": 753533}, {"year": 2010, "month": 5, "housingcost": 752948}, {"year": 2010, "month": 6, "housingcost": 752905}, {"year": 2010, "month": 7, "housingcost": 747421}, {"year": 2010, "month": 8, "housingcost": 749835}, {"year": 2010, "month": 9, "housingcost": 745043}, {"year": 2010, "month": 10, "housingcost": 740145}, {"year": 2010, "month": 11, "housingcost": 729555}, {"year": 2010, "month": 12, "housingcost": 723425}, {"year": 2011, "month": 1, "housingcost": 717090}, {"year": 2011, "month": 2, "housingcost": 710931}, {"year": 2011, "month": 3, "housingcost": 708052}, {"year": 2011, "month": 4, "housingcost": 710652}, {"year": 2011, "month": 5, "housingcost": 710050}, {"year": 2011, "month": 6, "housingcost": 707951}, {"year": 2011, "month": 7, "housingcost": 703503}, {"year": 2011, "month": 8, "housingcost": 703203}, {"year": 2011, "month": 9, "housingcost": 708180}, {"year": 2011, "month": 10, "housingcost": 716621}, {"year": 2011, "month": 11, "housingcost": 722151}, {"year": 2011, "month": 12, "housingcost": 727048}, {"year": 2012, "month": 1, "housingcost": 729029}, {"year": 2012, "month": 2, "housingcost": 734532}, {"year": 2012, "month": 3, "housingcost": 740856}, {"year": 2012, "month": 4, "housingcost": 744601}, {"year": 2012, "month": 5, "housingcost": 754131}, {"year": 2012, "month": 6, "housingcost": 768089}, {"year": 2012, "month": 7, "housingcost": 784459}, {"year": 2012, "month": 8, "housingcost": 798406}, {"year": 2012, "month": 9, "housingcost": 808916}, {"year": 2012, "month": 10, "housingcost": 814875}, {"year": 2012, "month": 11, "housingcost": 822115}, {"year": 2012, "month": 12, "housingcost": 823471}, {"year": 2013, "month": 1, "housingcost": 835371}, {"year": 2013, "month": 2, "housingcost": 851366}, {"year": 2013, "month": 3, "housingcost": 870745}, {"year": 2013, "month": 4, "housingcost": 885540}, {"year": 2013, "month": 5, "housingcost": 898776}, {"year": 2013, "month": 6, "housingcost": 905408}, {"year": 2013, "month": 7, "housingcost": 916835}, {"year": 2013, "month": 8, "housingcost": 918844}, {"year": 2013, "month": 9, "housingcost": 929794}, {"year": 2013, "month": 10, "housingcost": 943234}, {"year": 2013, "month": 11, "housingcost": 962237}, {"year": 2013, "month": 12, "housingcost": 982286}, {"year": 2014, "month": 1, "housingcost": 995139}, {"year": 2014, "month": 2, "housingcost": 1001621}, {"year": 2014, "month": 3, "housingcost": 1001616}, {"year": 2014, "month": 4, "housingcost": 1010458}, {"year": 2014, "month": 5, "housingcost": 1014765}, {"year": 2014, "month": 6, "housingcost": 1026441}, {"year": 2014, "month": 7, "housingcost": 1031190}, {"year": 2014, "month": 8, "housingcost": 1043898}, {"year": 2014, "month": 9, "housingcost": 1052056}, {"year": 2014, "month": 10, "housingcost": 1059515}, {"year": 2014, "month": 11, "housingcost": 1067153}, {"year": 2014, "month": 12, "housingcost": 1079843}, {"year": 2015, "month": 1, "housingcost": 1089158}, {"year": 2015, "month": 2, "housingcost": 1105137}, {"year": 2015, "month": 3, "housingcost": 1127750}, {"year": 2015, "month": 4, "housingcost": 1145464}, {"year": 2015, "month": 5, "housingcost": 1169186}, {"year": 2015, "month": 6, "housingcost": 1185422}, {"year": 2015, "month": 7, "housingcost": 1212900}, {"year": 2015, "month": 8, "housingcost": 1239022}, {"year": 2015, "month": 9, "housingcost": 1261145}, {"year": 2015, "month": 10, "housingcost": 1278591}, {"year": 2015, "month": 11, "housingcost": 1292552}, {"year": 2015, "month": 12, "housingcost": 1298658}, {"year": 2016, "month": 1, "housingcost": 1315696}, {"year": 2016, "month": 2, "housingcost": 1326167}, {"year": 2016, "month": 3, "housingcost": 1333668}, {"year": 2016, "month": 4, "housingcost": 1338016}, {"year": 2016, "month": 5, "housingcost": 1334389}, {"year": 2016, "month": 6, "housingcost": 1337950}, {"year": 2016, "month": 7, "housingcost": 1325512}, {"year": 2016, "month": 8, "housingcost": 1317333}, {"year": 2016, "month": 9, "housingcost": 1313035}, {"year": 2016, "month": 10, "housingcost": 1318060}, {"year": 2016, "month": 11, "housingcost": 1321272}, {"year": 2016, "month": 12, "housingcost": 1336242}, {"year": 2017, "month": 1, "housingcost": 1342025}, {"year": 2017, "month": 2, "housingcost": 1352126}, {"year": 2017, "month": 3, "housingcost": 1351268}, {"year": 2017, "month": 4, "housingcost": 1357633}, {"year": 2017, "month": 5, "housingcost": 1369005}, {"year": 2017, "month": 6, "housingcost": 1383621}, {"year": 2017, "month": 7, "housingcost": 1403345}, {"year": 2017, "month": 8, "housingcost": 1417726}, {"year": 2017, "month": 9, "housingcost": 1435170}, {"year": 2017, "month": 10, "housingcost": 1459099}, {"year": 2017, "month": 11, "housingcost": 1493742}, {"year": 2017, "month": 12, "housingcost": 1523682}, {"year": 2018, "month": 1, "housingcost": 1548083}, {"year": 2018, "month": 2, "housingcost": 1560277}, {"year": 2018, "month": 3, "housingcost": 1578558}, {"year": 2018, "month": 4, "housingcost": 1595579}, {"year": 2018, "month": 5, "housingcost": 1615965}, {"year": 2018, "month": 6, "housingcost": 1628436}, {"year": 2018, "month": 7, "housingcost": 1637628}, {"year": 2018, "month": 8, "housingcost": 1651406}, {"year": 2018, "month": 9, "housingcost": 1658845}, {"year": 2018, "month": 10, "housingcost": 1656704}, {"year": 2018, "month": 11, "housingcost": 1637751}, {"year": 2018, "month": 12, "housingcost": 1613433}, {"year": 2019, "month": 1, "housingcost": 1589883}, {"year": 2019, "month": 2, "housingcost": 1578136}, {"year": 2019, "month": 3, "housingcost": 1561214}, {"year": 2019, "month": 4, "housingcost": 1558057}, {"year": 2019, "month": 5, "housingcost": 1564995}, {"year": 2019, "month": 6, "housingcost": 1572135}, {"year": 2019, "month": 7, "housingcost": 1573254}, {"year": 2019, "month": 8, "housingcost": 1554433}, {"year": 2019, "month": 9, "housingcost": 1548725}, {"year": 2019, "month": 10, "housingcost": 1542026}, {"year": 2019, "month": 11, "housingcost": 1545686}, {"year": 2019, "month": 12, "housingcost": 1552540}, {"year": 2020, "month": 1, "housingcost": 1562959}, {"year": 2020, "month": 2, "housingcost": 1569672}, {"year": 2020, "month": 3, "housingcost": 1580001}, {"year": 2020, "month": 4, "housingcost": 1578941}, {"year": 2020, "month": 5, "housingcost": 1567988}, {"year": 2020, "month": 6, "housingcost": 1559598}, {"year": 2020, "month": 7, "housingcost": 1557266}, {"year": 2020, "month": 8, "housingcost": 1569255}], "covid": [{"year": 2020, "month": 1, "day": 22, "cases": 0}, {"year": 2020, "month": 1, "day": 23, "cases": 0}, {"year": 2020, "month": 1, "day": 24, "cases": 0}, {"year": 2020, "month": 1, "day": 25, "cases": 0}, {"year": 2020, "month": 1, "day": 26, "cases": 0}, {"year": 2020, "month": 1, "day": 27, "cases": 0}, {"year": 2020, "month": 1, "day": 28, "cases": 0}, {"year": 2020, "month": 1, "day": 29, "cases": 0}, {"year": 2020, "month": 1, "day": 30, "cases": 0}, {"year": 2020, "month": 1, "day": 31, "cases": 0}, {"year": 2020, "month": 2, "day": 1, "cases": 0}, {"year": 2020, "month": 2, "day": 2, "cases": 0}, {"year": 2020, "month": 2, "day": 3, "cases": 0}, {"year": 2020, "month": 2, "day": 4, "cases": 0}, {"year": 2020, "month": 2, "day": 5, "cases": 0}, {"year": 2020, "month": 2, "day": 6, "cases": 0}, {"year": 2020, "month": 2, "day": 7, "cases": 0}, {"year": 2020, "month": 2, "day": 8, "cases": 0}, {"year": 2020, "month": 2, "day": 9, "cases": 0}, {"year": 2020, "month": 2, "day": 10, "cases": 0}, {"year": 2020, "month": 2, "day": 11, "cases": 0}, {"year": 2020, "month": 2, "day": 12, "cases": 0}, {"year": 2020, "month": 2, "day": 13, "cases": 0}, {"year": 2020, "month": 2, "day": 14, "cases": 0}, {"year": 2020, "month": 2, "day": 15, "cases": 0}, {"year": 2020, "month": 2, "day": 16, "cases": 0}, {"year": 2020, "month": 2, "day": 17, "cases": 0}, {"year": 2020, "month": 2, "day": 18, "cases": 0}, {"year": 2020, "month": 2, "day": 19, "cases": 0}, {"year": 2020, "month": 2, "day": 20, "cases": 0}, {"year": 2020, "month": 2, "day": 21, "cases": 0}, {"year": 2020, "month": 2, "day": 22, "cases": 0}, {"year": 2020, "month": 2, "day": 23, "cases": 0}, {"year": 2020, "month": 2, "day": 24, "cases": 0}, {"year": 2020, "month": 2, "day": 25, "cases": 0}, {"year": 2020, "month": 2, "day": 26, "cases": 0}, {"year": 2020, "month": 2, "day": 27, "cases": 0}, {"year": 2020, "month": 2, "day": 28, "cases": 0}, {"year": 2020, "month": 2, "day": 29, "cases": 0}, {"year": 2020, "month": 3, "day": 1, "cases": 0}, {"year": 2020, "month": 3, "day": 2, "cases": 1}, {"year": 2020, "month": 3, "day": 3, "cases": 2}, {"year": 2020, "month": 3, "day": 4, "cases": 2}, {"year": 2020, "month": 3, "day": 5, "cases": 2}, {"year": 2020, "month": 3, "day": 6, "cases": 2}, {"year": 2020, "month": 3, "day": 7, "cases": 2}, {"year": 2020, "month": 3, "day": 8, "cases": 2}, {"year": 2020, "month": 3, "day": 9, "cases": 2}, {"year": 2020, "month": 3, "day": 10, "cases": 8}, {"year": 2020, "month": 3, "day": 11, "cases": 15}, {"year": 2020, "month": 3, "day": 12, "cases": 20}, {"year": 2020, "month": 3, "day": 13, "cases": 20}, {"year": 2020, "month": 3, "day": 14, "cases": 32}, {"year": 2020, "month": 3, "day": 15, "cases": 32}, {"year": 2020, "month": 3, "day": 16, "cases": 41}, {"year": 2020, "month": 3, "day": 17, "cases": 64}, {"year": 2020, "month": 3, "day": 18, "cases": 80}, {"year": 2020, "month": 3, "day": 19, "cases": 89}, {"year": 2020, "month": 3, "day": 20, "cases": 100}, {"year": 2020, "month": 3, "day": 21, "cases": 110}, {"year": 2020, "month": 3, "day": 22, "cases": 117}, {"year": 2020, "month": 3, "day": 23, "cases": 142}, {"year": 2020, "month": 3, "day": 24, "cases": 161}, {"year": 2020, "month": 3, "day": 25, "cases": 165}, {"year": 2020, "month": 3, "day": 26, "cases": 195}, {"year": 2020, "month": 3, "day": 27, "cases": 239}, {"year": 2020, "month": 3, "day": 28, "cases": 274}, {"year": 2020, "month": 3, "day": 29, "cases": 277}, {"year": 2020, "month": 3, "day": 30, "cases": 309}, {"year": 2020, "month": 3, "day": 31, "cases": 309}, {"year": 2020, "month": 4, "day": 1, "cases": 388}, {"year": 2020, "month": 4, "day": 2, "cases": 453}, {"year": 2020, "month": 4, "day": 3, "cases": 486}, {"year": 2020, "month": 4, "day": 4, "cases": 538}, {"year": 2020, "month": 4, "day": 5, "cases": 555}, {"year": 2020, "month": 4, "day": 6, "cases": 579}, {"year": 2020, "month": 4, "day": 7, "cases": 589}, {"year": 2020, "month": 4, "day": 8, "cases": 617}, {"year": 2020, "month": 4, "day": 9, "cases": 633}, {"year": 2020, "month": 4, "day": 10, "cases": 638}, {"year": 2020, "month": 4, "day": 11, "cases": 652}, {"year": 2020, "month": 4, "day": 12, "cases": 652}, {"year": 2020, "month": 4, "day": 13, "cases": 701}, {"year": 2020, "month": 4, "day": 14, "cases": 721}, {"year": 2020, "month": 4, "day": 15, "cases": 747}, {"year": 2020, "month": 4, "day": 16, "cases": 767}, {"year": 2020, "month": 4, "day": 17, "cases": 797}, {"year": 2020, "month": 4, "day": 18, "cases": 838}, {"year": 2020, "month": 4, "day": 19, "cases": 838}, {"year": 2020, "month": 4, "day": 20, "cases": 920}, {"year": 2020, "month": 4, "day": 21, "cases": 935}, {"year": 2020, "month": 4, "day": 22, "cases": 958}, {"year": 2020, "month": 4, "day": 23, "cases": 966}, {"year": 2020, "month": 4, "day": 24, "cases": 989}, {"year": 2020, "month": 4, "day": 25, "cases": 1019}, {"year": 2020, "month": 4, "day": 26, "cases": 1019}, {"year": 2020, "month": 4, "day": 27, "cases": 1080}, {"year": 2020, "month": 4, "day": 28, "cases": 1099}, {"year": 2020, "month": 4, "day": 29, "cases": 1136}, {"year": 2020, "month": 4, "day": 30, "cases": 1177}, {"year": 2020, "month": 5, "day": 1, "cases": 1197}, {"year": 2020, "month": 5, "day": 2, "cases": 1233}, {"year": 2020, "month": 5, "day": 3, "cases": 1233}, {"year": 2020, "month": 5, "day": 4, "cases": 1281}, {"year": 2020, "month": 5, "day": 5, "cases": 1315}, {"year": 2020, "month": 5, "day": 6, "cases": 1341}, {"year": 2020, "month": 5, "day": 7, "cases": 1377}, {"year": 2020, "month": 5, "day": 8, "cases": 1397}, {"year": 2020, "month": 5, "day": 9, "cases": 1425}, {"year": 2020, "month": 5, "day": 10, "cases": 1425}, {"year": 2020, "month": 5, "day": 11, "cases": 1464}, {"year": 2020, "month": 5, "day": 12, "cases": 1497}, {"year": 2020, "month": 5, "day": 13, "cases": 1515}, {"year": 2020, "month": 5, "day": 14, "cases": 1536}, {"year": 2020, "month": 5, "day": 15, "cases": 1575}, {"year": 2020, "month": 5, "day": 16, "cases": 1602}, {"year": 2020, "month": 5, "day": 17, "cases": 1602}, {"year": 2020, "month": 5, "day": 18, "cases": 1671}, {"year": 2020, "month": 5, "day": 19, "cases": 1687}, {"year": 2020, "month": 5, "day": 20, "cases": 1697}, {"year": 2020, "month": 5, "day": 21, "cases": 1738}, {"year": 2020, "month": 5, "day": 22, "cases": 1783}, {"year": 2020, "month": 5, "day": 23, "cases": 1833}, {"year": 2020, "month": 5, "day": 24, "cases": 1833}, {"year": 2020, "month": 5, "day": 25, "cases": 1833}, {"year": 2020, "month": 5, "day": 26, "cases": 1904}, {"year": 2020, "month": 5, "day": 27, "cases": 1963}, {"year": 2020, "month": 5, "day": 28, "cases": 2022}, {"year": 2020, "month": 5, "day": 29, "cases": 2061}, {"year": 2020, "month": 5, "day": 30, "cases": 2104}, {"year": 2020, "month": 5, "day": 31, "cases": 2104}, {"year": 2020, "month": 6, "day": 1, "cases": 2165}, {"year": 2020, "month": 6, "day": 2, "cases": 2188}, {"year": 2020, "month": 6, "day": 3, "cases": 2212}, {"year": 2020, "month": 6, "day": 4, "cases": 2244}, {"year": 2020, "month": 6, "day": 5, "cases": 2299}, {"year": 2020, "month": 6, "day": 6, "cases": 2330}, {"year": 2020, "month": 6, "day": 7, "cases": 2330}, {"year": 2020, "month": 6, "day": 8, "cases": 2394}, {"year": 2020, "month": 6, "day": 9, "cases": 2437}, {"year": 2020, "month": 6, "day": 10, "cases": 2475}, {"year": 2020, "month": 6, "day": 11, "cases": 2494}, {"year": 2020, "month": 6, "day": 12, "cases": 2533}, {"year": 2020, "month": 6, "day": 13, "cases": 2533}, {"year": 2020, "month": 6, "day": 14, "cases": 2553}, {"year": 2020, "month": 6, "day": 15, "cases": 2594}, {"year": 2020, "month": 6, "day": 16, "cases": 2625}, {"year": 2020, "month": 6, "day": 17, "cases": 2653}, {"year": 2020, "month": 6, "day": 18, "cases": 2678}, {"year": 2020, "month": 6, "day": 19, "cases": 2721}, {"year": 2020, "month": 6, "day": 20, "cases": 2721}, {"year": 2020, "month": 6, "day": 21, "cases": 2721}, {"year": 2020, "month": 6, "day": 22, "cases": 2825}, {"year": 2020, "month": 6, "day": 23, "cases": 2901}, {"year": 2020, "month": 6, "day": 24, "cases": 2961}, {"year": 2020, "month": 6, "day": 25, "cases": 2996}, {"year": 2020, "month": 6, "day": 26, "cases": 3049}, {"year": 2020, "month": 6, "day": 27, "cases": 3083}, {"year": 2020, "month": 6, "day": 28, "cases": 3083}, {"year": 2020, "month": 6, "day": 29, "cases": 3141}, {"year": 2020, "month": 6, "day": 30, "cases": 3232}, {"year": 2020, "month": 7, "day": 1, "cases": 3311}, {"year": 2020, "month": 7, "day": 2, "cases": 3376}, {"year": 2020, "month": 7, "day": 3, "cases": 3441}, {"year": 2020, "month": 7, "day": 4, "cases": 3536}, {"year": 2020, "month": 7, "day": 5, "cases": 3536}, {"year": 2020, "month": 7, "day": 6, "cases": 3599}, {"year": 2020, "month": 7, "day": 7, "cases": 3692}, {"year": 2020, "month": 7, "day": 8, "cases": 3743}, {"year": 2020, "month": 7, "day": 9, "cases": 3787}, {"year": 2020, "month": 7, "day": 10, "cases": 3846}, {"year": 2020, "month": 7, "day": 11, "cases": 3949}, {"year": 2020, "month": 7, "day": 12, "cases": 3949}, {"year": 2020, "month": 7, "day": 13, "cases": 4045}, {"year": 2020, "month": 7, "day": 14, "cases": 4168}, {"year": 2020, "month": 7, "day": 15, "cases": 4254}, {"year": 2020, "month": 7, "day": 16, "cases": 4333}, {"year": 2020, "month": 7, "day": 17, "cases": 4403}, {"year": 2020, "month": 7, "day": 18, "cases": 4465}, {"year": 2020, "month": 7, "day": 19, "cases": 4465}, {"year": 2020, "month": 7, "day": 20, "cases": 4551}, {"year": 2020, "month": 7, "day": 21, "cases": 4674}, {"year": 2020, "month": 7, "day": 22, "cases": 4776}, {"year": 2020, "month": 7, "day": 23, "cases": 4885}, {"year": 2020, "month": 7, "day": 24, "cases": 4957}, {"year": 2020, "month": 7, "day": 25, "cases": 5022}, {"year": 2020, "month": 7, "day": 26, "cases": 5022}, {"year": 2020, "month": 7, "day": 27, "cases": 5124}, {"year": 2020, "month": 7, "day": 28, "cases": 5198}, {"year": 2020, "month": 7, "day": 29, "cases": 5306}, {"year": 2020, "month": 7, "day": 30, "cases": 5398}, {"year": 2020, "month": 7, "day": 31, "cases": 5469}, {"year": 2020, "month": 8, "day": 1, "cases": 5544}, {"year": 2020, "month": 8, "day": 2, "cases": 5544}, {"year": 2020, "month": 8, "day": 3, "cases": 5683}, {"year": 2020, "month": 8, "day": 4, "cases": 5744}, {"year": 2020, "month": 8, "day": 5, "cases": 5758}, {"year": 2020, "month": 8, "day": 6, "cases": 5891}, {"year": 2020, "month": 8, "day": 7, "cases": 5978}, {"year": 2020, "month": 8, "day": 8, "cases": 6110}, {"year": 2020, "month": 8, "day": 9, "cases": 6110}, {"year": 2020, "month": 8, "day": 10, "cases": 6318}, {"year": 2020, "month": 8, "day": 11, "cases": 6431}, {"year": 2020, "month": 8, "day": 12, "cases": 6535}, {"year": 2020, "month": 8, "day": 13, "cases": 6640}, {"year": 2020, "month": 8, "day": 14, "cases": 6803}, {"year": 2020, "month": 8, "day": 15, "cases": 6952}, {"year": 2020, "month": 8, "day": 16, "cases": 6952}, {"year": 2020, "month": 8, "day": 17, "cases": 7150}, {"year": 2020, "month": 8, "day": 18, "cases": 7228}, {"year": 2020, "month": 8, "day": 19, "cases": 7321}, {"year": 2020, "month": 8, "day": 20, "cases": 7382}, {"year": 2020, "month": 8, "day": 21, "cases": 7472}, {"year": 2020, "month": 8, "day": 22, "cases": 7535}, {"year": 2020, "month": 8, "day": 23, "cases": 7535}, {"year": 2020, "month": 8, "day": 24, "cases": 7670}, {"year": 2020, "month": 8, "day": 25, "cases": 7788}, {"year": 2020, "month": 8, "day": 26, "cases": 7849}, {"year": 2020, "month": 8, "day": 27, "cases": 7911}, {"year": 2020, "month": 8, "day": 28, "cases": 7978}, {"year": 2020, "month": 8, "day": 29, "cases": 8074}, {"year": 2020, "month": 8, "day": 30, "cases": 8074}, {"year": 2020, "month": 8, "day": 31, "cases": 8169}, {"year": 2020, "month": 9, "day": 1, "cases": 8260}, {"year": 2020, "month": 9, "day": 2, "cases": 8311}, {"year": 2020, "month": 9, "day": 3, "cases": 8390}, {"year": 2020, "month": 9, "day": 4, "cases": 8452}, {"year": 2020, "month": 9, "day": 5, "cases": 8617}, {"year": 2020, "month": 9, "day": 6, "cases": 8617}, {"year": 2020, "month": 9, "day": 7, "cases": 8617}, {"year": 2020, "month": 9, "day": 8, "cases": 8750}, {"year": 2020, "month": 9, "day": 9, "cases": 8807}, {"year": 2020, "month": 9, "day": 10, "cases": 8895}, {"year": 2020, "month": 9, "day": 11, "cases": 8966}, {"year": 2020, "month": 9, "day": 12, "cases": 9077}, {"year": 2020, "month": 9, "day": 13, "cases": 9077}, {"year": 2020, "month": 9, "day": 14, "cases": 9166}, {"year": 2020, "month": 9, "day": 15, "cases": 9242}, {"year": 2020, "month": 9, "day": 16, "cases": 9264}, {"year": 2020, "month": 9, "day": 17, "cases": 9332}, {"year": 2020, "month": 9, "day": 18, "cases": 9332}, {"year": 2020, "month": 9, "day": 19, "cases": 9522}, {"year": 2020, "month": 9, "day": 20, "cases": 9522}, {"year": 2020, "month": 9, "day": 21, "cases": 9598}, {"year": 2020, "month": 9, "day": 22, "cases": 9625}, {"year": 2020, "month": 9, "day": 23, "cases": 9664}, {"year": 2020, "month": 9, "day": 24, "cases": 9714}, {"year": 2020, "month": 9, "day": 25, "cases": 9785}, {"year": 2020, "month": 9, "day": 26, "cases": 9843}, {"year": 2020, "month": 9, "day": 27, "cases": 9843}, {"year": 2020, "month": 9, "day": 28, "cases": 9897}, {"year": 2020, "month": 9, "day": 29, "cases": 9950}, {"year": 2020, "month": 9, "day": 30, "cases": 9990}, {"year": 2020, "month": 10, "day": 1, "cases": 10069}, {"year": 2020, "month": 10, "day": 2, "cases": 10126}, {"year": 2020, "month": 10, "day": 3, "cases": 10207}, {"year": 2020, "month": 10, "day": 4, "cases": 10207}, {"year": 2020, "month": 10, "day": 5, "cases": 10275}, {"year": 2020, "month": 10, "day": 6, "cases": 10309}, {"year": 2020, "month": 10, "day": 7, "cases": 10347}, {"year": 2020, "month": 10, "day": 8, "cases": 10395}, {"year": 2020, "month": 10, "day": 9, "cases": 10452}, {"year": 2020, "month": 10, "day": 10, "cases": 10510}, {"year": 2020, "month": 10, "day": 11, "cases": 10510}, {"year": 2020, "month": 10, "day": 12, "cases": 10510}], "historicalweather": [{"month": "Sep", "precipitation": 0.15, "temperature": 68.4}, {"month": "Mar", "precipitation": 3.96, "temperature": 53.3}, {"month": "Nov", "precipitation": 1.2, "temperature": 55.1}, {"month": "Apr", "precipitation": 0.3, "temperature": 59.9}, {"month": "Dec", "precipitation": 3.5, "temperature": 52.0}, {"month": "Jan", "precipitation": 4.77, "temperature": 52.4}, {"month": "Jun", "precipitation": 0.0, "temperature": 67.9}, {"month": "Oct", "precipitation": 0.0, "temperature": 61.9}, {"month": "Jul", "precipitation": 0.0, "temperature": 68.0}, {"month": "May", "precipitation": 1.46, "temperature": 58.9}, {"month": "Feb", "precipitation": 7.1, "temperature": 48.9}, {"month": "Aug", "precipitation": 0.0, "temperature": 70.0}]}